haystack_integrations/components/retrievers/py.typed
haystack_integrations/components/retrievers/qdrant/__init__.py
haystack_integrations/components/retrievers/qdrant/retriever.py
haystack_integrations/document_stores/py.typed
haystack_integrations/document_stores/qdrant/__init__.py
haystack_integrations/document_stores/qdrant/converters.py
haystack_integrations/document_stores/qdrant/document_store.py
haystack_integrations/document_stores/qdrant/filters.py
haystack_integrations/document_stores/qdrant/migrate_to_sparse.py
qdrant_haystack-10.0.0.dist-info/METADATA
qdrant_haystack-10.0.0.dist-info/WHEEL
qdrant_haystack-10.0.0.dist-info/licenses/LICENSE.txt
qdrant_haystack-10.0.0.dist-info/RECORD
