Metadata-Version: 2.4
Name: qdrant-haystack
Version: 10.0.0
Summary: An integration of Qdrant ANN vector database backend with Haystack
Project-URL: Source, https://github.com/deepset-ai/haystack-core-integrations
Project-URL: Documentation, https://github.com/deepset-ai/haystack-core-integrations/blob/main/integrations/qdrant/README.md
Project-URL: Issues, https://github.com/deepset-ai/haystack-core-integrations/issues
Author-email: Kacper Łukawski <kacper.lukawski@qdrant.com>, Anush Shetty <anush.shetty@qdrant.com>
License-Expression: Apache-2.0
License-File: LICENSE.txt
Classifier: Development Status :: 4 - Beta
Classifier: License :: OSI Approved :: Apache Software License
Classifier: Programming Language :: Python
Classifier: Programming Language :: Python :: 3.10
Classifier: Programming Language :: Python :: 3.11
Classifier: Programming Language :: Python :: 3.12
Classifier: Programming Language :: Python :: 3.13
Classifier: Programming Language :: Python :: Implementation :: CPython
Classifier: Programming Language :: Python :: Implementation :: PyPy
Requires-Python: >=3.10
Requires-Dist: haystack-ai>=2.22.0
Requires-Dist: qdrant-client>=1.12.0
